llm_output_parser/__init__.py
llm_output_parser/json_parser.py
llm_output_parser/jsons_parser.py
llm_output_parser/xml_parser.py
llm_output_parser-0.3.0.dist-info/licenses/LICENSE
llm_output_parser-0.3.0.dist-info/METADATA
llm_output_parser-0.3.0.dist-info/WHEEL
llm_output_parser-0.3.0.dist-info/top_level.txt
llm_output_parser-0.3.0.dist-info/RECORD
