Metadata-Version: 2.4
Name: llm-output-parser
Version: 0.3.0
Summary: Extract and parse JSON from unstructured text outputs from LLMs
Author-email: Alex Kameni <Kamenialexnea@gmail.com>
License: MIT
Project-URL: Homepage, https://github.com/KameniAlexNea/llm-output-parser
Project-URL: Repository, https://github.com/KameniAlexNea/llm-output-parser
Keywords: llm,json,parsing,extraction,nlp,ai,language models
Classifier: Programming Language :: Python :: 3
Classifier: Programming Language :: Python :: 3.8
Classifier: Programming Language :: Python :: 3.9
Classifier: Programming Language :: Python :: 3.10
Classifier: Programming Language :: Python :: 3.11
Classifier: License :: OSI Approved :: MIT License
Classifier: Operating System :: OS Independent
Classifier: Development Status :: 4 - Beta
Classifier: Intended Audience :: Developers
Classifier: Topic :: Software Development :: Libraries :: Python Modules
Classifier: Topic :: Text Processing :: Markup
Requires-Python: >=3.8
License-File: LICENSE
Provides-Extra: dev
Requires-Dist: pytest>=7.0.0; extra == "dev"
Requires-Dist: pytest-cov>=4.0.0; extra == "dev"
Requires-Dist: coveralls>=3.3.1; extra == "dev"
Dynamic: license-file
